sfisop/messaging_sdk/__init__.py
sfisop/messaging_sdk/configuration.py
sfisop/messaging_sdk/publisher.py
sfisop/messaging_sdk/publisher_sample.py
sfisop/messaging_sdk/subscriber.py
sfisop/messaging_sdk/subscriber_sample.py
sfisop_messaging_sdk-1.0.3.dist-info/LICENSE
sfisop_messaging_sdk-1.0.3.dist-info/METADATA
sfisop_messaging_sdk-1.0.3.dist-info/WHEEL
sfisop_messaging_sdk-1.0.3.dist-info/RECORD
