Metadata-Version: 2.1
Name: sfisop-messaging-sdk
Version: 1.0.3
Summary: SDK for the SmartOcean Platform Messaging Service
License: MIT
Author: The SmartOcean Consortium
Requires-Python: >=3.9,<4.0.0
Classifier: License :: OSI Approved :: MIT License
Classifier: Programming Language :: Python :: 3
Classifier: Programming Language :: Python :: 3.9
Classifier: Programming Language :: Python :: 3.10
Classifier: Programming Language :: Python :: 3.11
Classifier: Programming Language :: Python :: 3.12
Classifier: Programming Language :: Python :: 3.13
Requires-Dist: annotated-types (>=0.6.0,<0.7.0)
Requires-Dist: certifi (==2024.7.4)
Requires-Dist: charset-normalizer (>=3.3.2,<4.0.0)
Requires-Dist: dnspython (>=2.6.1,<3.0.0)
Requires-Dist: idna (>=3.7,<4.0)
Requires-Dist: paho-mqtt (>=2.1.0,<3.0.0)
Requires-Dist: pydantic-core (>=2.16.3,<3.0.0)
Requires-Dist: pymongo (==4.6.3)
Requires-Dist: python-dateutil (>=2.9.0.post0,<3.0.0)
Requires-Dist: python-decouple (>=3.8,<4.0)
Requires-Dist: pyyaml (>=6.0.1,<7.0.0)
Requires-Dist: requests (>=2.32.0,<3.0.0)
Requires-Dist: six (>=1.16.0,<2.0.0)
Requires-Dist: urllib3 (>=2.2.2,<3.0.0)
